{
  "Become an Organizer": "Become an Organizer3",
  "Sign Up": "Sign Up3",
  "Event Subcategory": "Event Subcategory",
  "Recent View": "Recent View,Recent View",
  "All Letest Event": "All Letest Event,",
  "Join Our Newsletter and Get updated": "Join Our Newsletter and Get updated",
  "We only send interesting and  relevant emails": "We only send interesting and  relevant emails",
  "Enter your email": "Enter your email",
  "Subscribe": "Subscribe",
  "Check now": "Check now",
  "Event not Found!": "Event not Found!",
  "Back to Home": "Back to Home,Back to Home",
  "Home": "Home",
  "About Us": "About Us",
  "Events": "Events",
  "Contact Us": "Contact Us",
  "Search your event": "Search your event",
  "Sign In": "Sign In",
  "Hi": "Hi",
  "Account and Settings": "Account and Settings",
  "Location Payment and more": "Location, Payment and more",
  "Your Orders": "Your Orders",
  "View all your bookings and purchases": "View all your bookings and purchases",
  "Wishlist": "Wishlist",
  "View all your watch list": "View all your watch list",
  "Sign Out": "Sign Out",
  "Welcome Back": "Welcome Back",
  "Still don't have an account": "Still don't have an account",
  "Email": "Email",
  "Password": "Password",
  "Keep me logged in": "Keep me logged in",
  "Forget password": "Forget password",
  "OR": "OR",
  "Login with Google": "Login with Google",
  "Login with Facebook": "Login with Facebook",
  "Don't have an account": "Don't have an account",
  "Register": "Register",
  "Already have an account": "Already have an account",
  "First Name": "First Name",
  "Last Name": "Last Name",
  "Confirm Password": "Confirm Password",
  "By hitting the 'Register' button, you agree to the": "By hitting the 'Register' button, you agree to the",
  "Terms conditions": "Terms conditions",
  "&": "&",
  "Privacy Policy": "Privacy Policy",
  "Have an account": "Have an account",
  "Send Verification Code": "Send Verification Code",
  "Enter your verification code": "Enter your verification code",
  "Send the code again": "Send the code again",
  "Verify": "Verify",
  "Submit": "Submit",
  "Settings": "Settings",
  "Join Our": "Join Our",
  "Newsletter": "Newsletter",
  "Get updated": "Get updated",
  "We only send interesting and relevant emails": "We only send interesting and relevant emails",
  "Follow Us": "Follow Us",
  "Cookies": "Cookies",
  "Features Categories": "Features Categories",
  "Booked": "Booked",
  "Popular Events": "Popular Events",
  "see more": "see more",
  "All Latest Event": "All Latest Event",
  "Today": "Today",
  "Tomorrow": "Tomorrow",
  "This Week": "This Week",
  "This Month": "This Month",
  "Live": "Live",
  "We have": "We have",
  "Awards Winning": "Awards Winning",
  "Create an Event": "Create an Event",
  "About us": "About us",
  "Years of Experience": "Years of Experience",
  "25k": "25k",
  "Become Organizer": "Become Organizer",
  "Company Information": "Company Information",
  "Phone Number": "Phone Number",
  "Email address": "Email address",
  "Country": "Country",
  "Country Name": "Country Name",
  "Town/ City": "Town/ City",
  "City Name": "City Name",
  "Address": "Address",
  "Tax ID/Business Registration Number": "Tax ID/Business Registration Number",
  "Photo attachment": "Photo attachment",
  "Company Documents": "Company Documents",
  "At least Size": "At least Size",
  "Drop files to upload": "Drop files to upload",
  "Browse": "Browse",
  "Company Logo": "Company Logo",
  "Describe about your Organization": "Describe about your Organization",
  "Description": "Description",
  "I agree with the": "I agree with the",
  "Discard": "Discard",
  "Categories": "Categories",
  "All Categories": "All Categories",
  "Get Ready to Start It’s Fast": "Get Ready to Start It’s Fast",
  "Free Contacts us": "Free Contacts us",
  "Our Address": "Our Address",
  "Contact Info": "Contact Info",
  "Live Support": "Live Suppor343",
  "Organize By": "Organize By",
  "Location": "Location",
  "Share with you friends": "Share with you friends",
  "You might also Enjoy These": "You might also Enjoy These",
  "Search": "Search",
  "Sort By": "Sort By",
  "Category": "Category,",
  "Cities": "Cities",
  "Price": "Price",
  "Check Now": " Check Now",
  "Total Events": "Total Events",
  "Active Events": "Active Events",
  "Total Sales": "Total Sales",
  "View All": " View All",
  "Dashboard": "Dashboard",
  "My Events": "My Events",
  "My Ticket": "My Ticket",
  "Check Ticket": "Check Ticket",
  "Change Password": "Change Password",
  "Create Event": "Create Event",
  "Loading": "Loading",
  "We only support .JPG, .JPEG, or .PNG file": "We only support .JPG, .JPEG, or .PNG file",
  "Upload Photo": "Upload Photo",
  "Name": " Name",
  "Enter your name": " Enter your name",
  "Enter your Email": "Enter your Email",
  "Enter your phone number": "Enter your phone number",
  "City": "City",
  "Enter your full address": "Enter your full address",
  "Postal Code": "Postal Code",
  "Enter postal code": "Enter postal code",
  "Public": "Public",
  "No! Cancel": "No! Cancel",
  "Ticket Purchases": "Ticket Purchases",
  "Search by name, email, or others": "Search by name, email, or others",
  "Filters": "Filters",
  "Event Name": "Event Name",
  "Date": "Date",
  "Status": "Status",
  "Action": "Action",
  "expired": "expired",
  "Active": "Active",
  "Payment Information": "Payment Information",
  "Payment by": "Payment by",
  "Order Summary": "Order Summary",
  "Unit Price": "Unit Price",
  "QTY": "QTY",
  "Total": "Total",
  "Password Change": "Password Change",
  "Give me correct password and change password": "Give me correct password and change password",
  "Old Password": "Old Password",
  "New Password": "New Password",
  "Pause": "Pause",
  "Cancel": "Cancel",
  "Are you Sure": "Are you Sure",
  "Pause this Event": "Pause this Event",
  "All Events": "All Events",
  "Filter": "Filter",
  "This Year": "This Year",
  "Sales": "Sales",
  "Start Date": "Start Date",
  "Event Information": "Event Information",
  "Event Title": "Event Title",
  "Event name here": "Event name here",
  "Event Image": "Event Image",
  "Cover of at least Size": "Cover of at least Size",
  "Event Date And Time": "Event Date And Time",
  "Select Event Date": "Select Event Date",
  "Event Duration": "Event Duration",
  "Type duration in Hour": "Type duration in Hour",
  "Select Category": "Select Category",
  "Select Sub Category": "Select Sub Category",
  "Available Sit Provide": "Available Sit Provide",
  "How Many Sits": "How Many Sits",
  "Ticket Price": "Ticket Price",
  "Select City": "Select City",
  "Select Venue": "Select Venue",
  "Description before banner": "Description before banner",
  "Description after Banner": "Description after Banner",
  "Type your address": "Type your address",
  "Google Map Embed Link": "Google Map Embed Link",
  "Map Link": "Map Link",
  "Event": "Event",
  "Create": "Create",
  "Update": "Update",
  "My Tickets": "My Tickets",
  "Organizer": "Organizer",
  "Date and Time": "Date and Time",
  "Venue": "Venue",
  "Mobile": "Mobile",
  "Scan your QR Code": "Scan your QR Code",
  "Print Now": "Print Now",
  "Download": "Download",
  "Ticket not Found!": "Ticket not Found!",
  "Sent Review for": "Sent Review for",
  "Your email address will not be published. Required fields are marked": "Your email address will not be published. Required fields are marked",
  "Write your feedback": "Write your feedback",
  "Review list": "Review list",
  "Let’s check your today": "Let’s check your today",
  "QR Code Scanner": "QR Code Scanner",
  "QR Code": "QR Code",
  "Quantity": " Quantity",
  "Total Price": "Total Price",
  "My Wish List": " My Wish List",
  "No Wishlist": "No Wishlist",
  "Privacy policy": "Privacy policy",
  "Something went Wrong": "Something went Wrong",
  "Send": "Send",
  "Billing information": "Billing information",
  "First name": "First name",
  "Last name": "Last name",
  "Phone": " Phone",
  "Checkout": " Checkout",
  "Card Number": "Card Number",
  "Expired Date": "Expired Date",
  "By selecting place order. I agree to the": "By selecting place order. I agree to the",
  "Terms of Service": "Terms of Service",
  "By": "By",
  "Promo Code": "Promo Code",
  "Enter code": "Enter code",
  "Apply": "Apply",
  "Tickets Quantity": "Tickets Quantity",
  "Sales end on": "Sales end on",
  "Place order": "Place order",
  "ticket": "ticket",
  "Thank you": "Thank you",
  "Purchase Ticket": "Purchase Ticket",
  "View Ticket": "View Ticket",
  "Get ticket": "Get ticket",
  "Review": "Review",
  "Total Earning": "Total Earning",
  "Last Month Earning": "Last Month Earning",
  "Terms and Conditions": "Terms and Conditions",
  "Account Setting": "Account Setting"
}